mksc/__init__.py
mksc/core/__init__.py
mksc/core/cmd.py
mksc/core/prepocess.py
mksc/core/start.py
mksc/feature/__init__.py
mksc/feature/engineering.py
mksc/feature/transform.py
mksc/feature/binning/__init__.py
mksc/feature/binning/binning.py
mksc/feature/binning/woe.py
mksc/feature/seletction/__init__.py
mksc/feature/seletction/model.py
mksc/feature/seletction/statistics.py
mksc/feature/values/__init__.py
mksc/feature/values/abnormal.py
mksc/feature/values/missing.py
mksc/feature/values/normalization.py
mksc/feature/values/scale.py
mksc/feature/values/standard.py
mksc/score/__init__.py
mksc/score/card.py
mksc/score/score.py
mksc/score/transform.py
mksc/step/__init__.py
mksc/step/eda.py
mksc/step/feature.py
mksc/template/custom.py
mksc/template/main.py
mksc/template/predict.py
mksc/template/config/configuration.ini
mksc/template/models/dnn.py
mksc/template/models/lgb.py
mksc/template/models/svm.py
mksc/utils/__init__.py
mksc/utils/reader.py
mksc/utils/saver.py
mksc/utils/tools.py
mksc-3.0.0.dist-info/LICENSE
mksc-3.0.0.dist-info/METADATA
mksc-3.0.0.dist-info/WHEEL
mksc-3.0.0.dist-info/entry_points.txt
mksc-3.0.0.dist-info/top_level.txt
mksc-3.0.0.dist-info/RECORD
