Metadata-Version: 2.1
Name: mksc
Version: 3.0.0
Summary: It is used to quickly build a scorecard project and dichotomy model package.
Home-page: https://github.com/HelloCoyen/mksc.git
Author: wuhaoyu
Author-email: wuhaoyu96@163.com
License: UNKNOWN
Platform: UNKNOWN
Classifier: Programming Language :: Python :: 3
Classifier: License :: OSI Approved :: MIT License
Classifier: Operating System :: OS Independent
Requires-Python: >=3.4
Requires-Dist: numpy
Requires-Dist: pandas
Requires-Dist: sklearn
